music_riff/__init__.py
music_riff/cant_use_.py
music_riff/fix_bug_.py
music_riff/sandbox1_.py
music_riff/utils_.py
package_name/__init__.py
package_name/cant_use_.py
package_name/fix_bug_.py
package_name/sandbox1_.py
package_name/utils_.py
play_audio/__init__.py
play_audio/cant_use_.py
play_audio/fix_bug_.py
play_audio/sandbox1_.py
play_audio/utils_.py
play_audio_file/__init__.py
play_audio_file/cant_use_.py
play_audio_file/fix_bug_.py
play_audio_file/sandbox1_.py
play_audio_file/utils_play_audio_file.py
riff_music/__init__.py
riff_music/cant_use_.py
riff_music/fix_bug_.py
riff_music/sandbox1_.py
riff_music/utils_riff.py
play_audio_file-0.1.0rc3.dist-info/LICENSE
play_audio_file-0.1.0rc3.dist-info/METADATA
play_audio_file-0.1.0rc3.dist-info/WHEEL
play_audio_file-0.1.0rc3.dist-info/top_level.txt
play_audio_file-0.1.0rc3.dist-info/RECORD
