Metadata-Version: 2.1
Name: play_audio_file
Version: 0.1.0rc3
Summary: play audio with different engines(packages)
Author: Norathee Lert
License: MIT
License-File: LICENSE
Requires-Dist: pandas
Requires-Dist: os-toolkit >=0.1.1
Requires-Dist: py-string-tool >=0.1.3
Requires-Dist: python-wizard >=0.1.1
